nbapy/__init__.py
nbapy/constants.py
nbapy/draft_combine.py
nbapy/game.py
nbapy/league.py
nbapy/nba_api.py
nbapy/player.py
nbapy/scoreboard.py
nbapy/shot_chart.py
nbapy/team.py
nbapy-1.1.8.dist-info/LICENSE
nbapy-1.1.8.dist-info/METADATA
nbapy-1.1.8.dist-info/WHEEL
nbapy-1.1.8.dist-info/top_level.txt
nbapy-1.1.8.dist-info/RECORD
