Metadata-Version: 2.1
Name: nbapy
Version: 1.1.8
Summary: Python client for NBA statistics located at nba.com
Home-page: https://github.com/jtpavlock/nbapy
License: UNKNOWN
Platform: UNKNOWN
Requires-Python: >=3.6
Provides-Extra: dev
